Controle/Controle.v
module Controle(
    input [3:0] instrucao,
    output reg Branch,
    output reg MemRead,
    output reg MemtoReg,
    output reg [1:0] ALUOp,
    output reg MemWrite,
    output reg ALUSrc,
    output reg RegWrite
);
//Operações imediatas
localparam ADD = 4'b0000; // Soma A e B, armazena no endereço indicado no imediato #
localparam SUB = 4'b0001; // Subtrai B de A, armazena no endereço indicado no imediato #
localparam LDA = 4'b0010; // Carrega o valor do endereço indicado no imediato # para o registrador A
localparam STA = 4'b0011; // Armazena o valor de A no endereço indicado no imediato #
localparam LDB = 4'b0100; // Carrega o valor do endereço indicado no imediato # para o registrador B
localparam STB = 4'b0101; // Armazena o valor de B no endereço indicado no imediato #
localparam LDC = 4'b0110; // Carrega uma constante no registrador A;
localparam JMP = 4'b0111; // Jump condicionado ao conteúdo de A, se 0, então salta para o endereço apontado 
                // pelo endereço indicado no imediato #

//*****************************
//localparam OR = 4'b1000;
//localparam AND = 4'b1001;
//localparam BEQ =


/*
// Agora podemos ter:
2'b00 = Operações aritméticas (ADD, ADDI)
2'b01 = Operações de comparação (SUB, SLT, BEQ)  
2'b10 = Operações lógicas (AND, ANDI)
2'b11 = Operações lógicas (OR, ORI)
*/



always @(*)begin 
    //Inicializando como valores que indicam não operação
    Branch = 1'b0;
    MemRead = 1'b0;
    MemtoReg = 1'b0;
    ALUOp = 2'b00; //add modo padrão 
    MemWrite = 1'b0;
    ALUSrc = 1'b0;
    RegWrite = 1'b0;

    case (instrucao)
        ADD: begin // ADD nessa arquitetura é um add imediato
            ALUSrc   = 1'b1;   // Usa imediato como operando
            RegWrite = 1'b1;   // Escreve no registrador
            ALUOp    = 2'b00;  // Operação de soma
        end
        
        SUB: begin
            ALUOp = 2'b01;
            RegWrite = 1'b1;
        end

        LDA: begin
            MemRead = 1'b1; // Lê da memoria
            MemtoReg = 1'b1; // Dado vem para memoria 
            ALUSrc = 1'b1; // usa o imediato para endereco
            RegWrite = 1'b1; // Escreve no registrador
            ALUOp = 2'b00;  // Soma para calculo de endereco????? 
        end

        LDB: begin
            MemRead = 1'b1; 
            MemtoReg = 1'b1; 
            ALUSrc = 1'b1; 
            RegWrite = 1'b1; 
            ALUOp = 2'b00;
        end

        LDC: begin
            MemRead = 1'b1; 
            MemtoReg = 1'b1; 
            ALUSrc = 1'b1; 
            RegWrite = 1'b1; 
            ALUOp = 2'b00;
        end

        STA: begin
            MemWrite = 1'b1;
            ALUSrc = 1'b1;
            ALUOp = 2'b00; 
        end

        STB: begin
            MemWrite = 1'b1;
            ALUSrc = 1'b1;
            ALUOp = 2'b00; 
        end

        JMP: begin
            Branch = 1'b1;
            // AluOP don't care
        end

        default: begin
            Branch = 1'b0;
            MemRead = 1'b0;
            MemtoReg = 1'b0;
            ALUOp = 2'b00; //add modo padrão 
            MemWrite = 1'b0;
            ALUSrc = 1'b0;
            RegWrite = 1'b0;
        end
    endcase

end


endmodule

testes_V/Controle/testbench.v
module testbench;

reg [3:0] instrucao;
wire Branch, MemRead, MemtoReg, MemWrite, ALUSrc, RegWrite;
wire [1:0] ALUOp;

Controle controle(
    .instrucao(instrucao),
    .Branch(Branch),
    .MemRead(MemRead),
    .MemtoReg(MemtoReg),
    .MemWrite(MemWrite),
    .ALUSrc(ALUSrc),
    .RegWrite(RegWrite),
    .ALUOp(ALUOp)
    );

localparam ADD = 4'b0000; // Soma A e B, armazena no endereço indicado no imediato #
localparam SUB = 4'b0001; // Subtrai B de A, armazena no endereço indicado no imediato #
localparam LDA = 4'b0010; // Carrega o valor do endereço indicado no imediato # para o registrador A
localparam STA = 4'b0011; // Armazena o valor de A no endereço indicado no imediato #
localparam LDB = 4'b0100; // Carrega o valor do endereço indicado no imediato # para o registrador B
localparam STB = 4'b0101; // Armazena o valor de B no endereço indicado no imediato #
localparam LDC = 4'b0110; // Carrega uma constante no registrador A;
localparam JMP = 4'b0111;


initial begin 

    $dumpfile("teste.vcd");
    $dumpvars(0,testbench);

    $monitor("in: %b|ALUop: %b|Branch: %b|MemRead: %b|MemtoReg: %b|MemWrite: %b|ALUSrc: %b|RegWrite: %b", instrucao,
    ALUOp,Branch, MemRead, MemtoReg, MemWrite, ALUSrc, RegWrite);
    instrucao = 4'b0000;
    #2 instrucao = ADD;
    #2 instrucao = SUB;
    #2 instrucao = STA;
    #2 instrucao = STB;
    #2 instrucao = LDA;
    #2 instrucao = LDB;
    #2 instrucao = LDC;
    #2 instrucao = JMP;
    
    #2 $finish;
end



endmodule

testes_V/Controle/teste.vcd
$date
	Tue Nov 11 09:05:05 2025
$end
$version
	Icarus Verilog
$end
$timescale
	1s
$end
$scope module testbench $end
$var wire 1 ! RegWrite $end
$var wire 1 " MemtoReg $end
$var wire 1 # MemWrite $end
$var wire 1 $ MemRead $end
$var wire 1 % Branch $end
$var wire 1 & ALUSrc $end
$var wire 2 ' ALUOp [1:0] $end
$var parameter 4 ( ADD $end
$var parameter 4 ) JMP $end
$var parameter 4 * LDA $end
$var parameter 4 + LDB $end
$var parameter 4 , LDC $end
$var parameter 4 - STA $end
$var parameter 4 . STB $end
$var parameter 4 / SUB $end
$var reg 4 0 instrucao [3:0] $end
$scope module controle $end
$var wire 4 1 instrucao [3:0] $end
$var parameter 4 2 ADD $end
$var parameter 4 3 JMP $end
$var parameter 4 4 LDA $end
$var parameter 4 5 LDB $end
$var parameter 4 6 LDC $end
$var parameter 4 7 STA $end
$var parameter 4 8 STB $end
$var parameter 4 9 SUB $end
$var reg 2 : ALUOp [1:0] $end
$var reg 1 & ALUSrc $end
$var reg 1 % Branch $end
$var reg 1 $ MemRead $end
$var reg 1 # MemWrite $end
$var reg 1 " MemtoReg $end
$var reg 1 ! RegWrite $end
$upscope $end
$upscope $end
$enddefinitions $end
$comment Show the parameter values. $end
$dumpall
b1 9
b101 8
b11 7
b110 6
b100 5
b10 4
b111 3
b0 2
b1 /
b101 .
b11 -
b110 ,
b100 +
b10 *
b111 )
b0 (
$end
#0
$dumpvars
b0 :
b0 1
b0 0
b0 '
1&
0%
0$
0#
0"
1!
$end
#4
b1 '
b1 :
1!
0&
b1 0
b1 1
#6
1&
1#
0!
b0 '
b0 :
b11 0
b11 1
#8
1&
1#
b101 0
b101 1
#10
1!
1"
1$
1&
0#
b10 0
b10 1
#12
1!
1&
1"
1$
b100 0
b100 1
#14
1!
1&
1"
1$
b110 0
b110 1
#16
1%
0!
0&
0"
0$
b111 0
b111 1
