testes_V/Ram/Ram.v
module Ram(
    input clk,
    input reset,
    input MemWrite,
    input MemRead,
    input [3:0] Address,
    input [7:0] WriteData,
    output [7:0] MemData_out
);

integer k; 
reg [7:0] memoria_dados[0:15];

always @(posedge clk) begin
    if(reset)begin
        for(k=0; k<16; k=k+1)begin
            memoria_dados[k] <= 8'b0000_0000;
        end
    end else if(MemWrite)begin 
        memoria_dados[Address] <= WriteData;
    end
end

assign MemData_out = (MemRead) ? memoria_dados[Address] : 8'b0000_0000;  

endmodule

testes_V/Ram/testbench.v
`timescale 1ns / 1ps

module testbench;

    // Entradas
    reg clk;
    reg reset;
    reg MemWrite;
    reg MemRead;
    reg [3:0] Address;
    reg [7:0] WriteData;

    // Saídas
    wire [7:0] MemData_out;

    // Instancia o módulo RAM
    Ram uut (
        .clk(clk),
        .reset(reset),
        .MemWrite(MemWrite),
        .MemRead(MemRead),
        .Address(Address),
        .WriteData(WriteData),
        .MemData_out(MemData_out)
    );

    // Geração do clock: alterna a cada 5 ns (período = 10 ns)
    always #5 clk = ~clk;

    // Procedimento principal
    initial begin
        // Inicializa os sinais
        $dumpfile("teste.vcd");
        $dumpvars(0,testbench);

        clk = 0;
        reset = 0;
        MemWrite = 0;
        MemRead = 0;
        Address = 0;
        WriteData = 0;

        // ---------- Teste 1: RESET ----------
        $display("\n=== TESTE 1: RESET ===");
        reset = 1;
        #10; // Espera um ciclo de clock
        reset = 0;

        // ---------- Teste 2: ESCRITA ----------
        $display("\n=== TESTE 2: ESCRITA ===");
        @(posedge clk);
        MemWrite = 1;
        Address = 4'b0001;
        WriteData = 8'b1010_1010;
        @(posedge clk);
        MemWrite = 0;

        @(posedge clk);
        MemWrite = 1;
        Address = 4'b0010;
        WriteData = 8'b1111_0000;
        @(posedge clk);
        MemWrite = 0;

        // ---------- Teste 3: LEITURA ----------
        $display("\n=== TESTE 3: LEITURA ===");
        @(posedge clk);
        MemRead = 1;
        Address = 4'b0010;
        #1; // pequeno atraso para leitura estabilizar
        $display("Leitura [5] = %b (esperado: 10101010)", MemData_out);

        @(posedge clk);
        Address = 4'b0001;
        #1;
        $display("Leitura [10] = %b (esperado: 11110000)", MemData_out);

        // ---------- Teste 4: Leitura de endereço não escrito ----------
        @(posedge clk);
        Address = 4'b0000;
        #1;
        $display("Leitura [3] = %b (esperado: 00000000)", MemData_out);
        MemRead = 0;

        // ---------- Fim da simulação ----------
        $display("\n=== TESTE FINALIZADO ===\n");
        #10;

        #2 $finish;
    end

endmodule

testes_V/Ram/teste.vcd
$date
	Wed Nov 12 07:44:00 2025
$end
$version
	Icarus Verilog
$end
$timescale
	1ps
$end
$scope module testbench $end
$var wire 8 ! MemData_out [7:0] $end
$var reg 4 " Address [3:0] $end
$var reg 1 # MemRead $end
$var reg 1 $ MemWrite $end
$var reg 8 % WriteData [7:0] $end
$var reg 1 & clk $end
$var reg 1 ' reset $end
$scope module uut $end
$var wire 4 ( Address [3:0] $end
$var wire 1 # MemRead $end
$var wire 1 $ MemWrite $end
$var wire 8 ) WriteData [7:0] $end
$var wire 1 & clk $end
$var wire 1 ' reset $end
$var wire 8 * MemData_out [7:0] $end
$var integer 32 + k [31:0] $end
$upscope $end
$upscope $end
$enddefinitions $end
$comment Show the parameter values. $end
$dumpall
$end
#0
$dumpvars
bx +
b0 *
b0 )
b0 (
1'
0&
b0 %
0$
0#
b0 "
b0 !
$end
#5000
b10000 +
1&
#10000
0&
0'
#15000
b10101010 %
b10101010 )
b1 "
b1 (
1$
1&
#20000
0&
#25000
0$
1&
#30000
0&
#35000
b11110000 %
b11110000 )
b10 "
b10 (
1$
1&
#40000
0&
#45000
0$
1&
#50000
0&
#55000
b11110000 !
b11110000 *
1#
1&
#60000
0&
#65000
b10101010 !
b10101010 *
b1 "
b1 (
1&
#70000
0&
#75000
b0 !
b0 *
b0 "
b0 (
1&
#76000
0#
